torchseg/__init__.py
torchseg/base/__init__.py
torchseg/base/heads.py
torchseg/base/initialization.py
torchseg/base/model.py
torchseg/base/modules.py
torchseg/decoders/__init__.py
torchseg/decoders/deeplabv3/__init__.py
torchseg/decoders/deeplabv3/decoder.py
torchseg/decoders/deeplabv3/model.py
torchseg/decoders/fpn/__init__.py
torchseg/decoders/fpn/decoder.py
torchseg/decoders/fpn/model.py
torchseg/decoders/linknet/__init__.py
torchseg/decoders/linknet/decoder.py
torchseg/decoders/linknet/model.py
torchseg/decoders/manet/__init__.py
torchseg/decoders/manet/decoder.py
torchseg/decoders/manet/model.py
torchseg/decoders/pan/__init__.py
torchseg/decoders/pan/decoder.py
torchseg/decoders/pan/model.py
torchseg/decoders/pspnet/__init__.py
torchseg/decoders/pspnet/decoder.py
torchseg/decoders/pspnet/model.py
torchseg/decoders/unet/__init__.py
torchseg/decoders/unet/decoder.py
torchseg/decoders/unet/model.py
torchseg/decoders/unetplusplus/__init__.py
torchseg/decoders/unetplusplus/decoder.py
torchseg/decoders/unetplusplus/model.py
torchseg/encoders/__init__.py
torchseg/encoders/mix_transformer.py
torchseg/encoders/supported.py
torchseg/encoders/timm.py
torchseg/losses/__init__.py
torchseg/losses/_functional.py
torchseg/losses/constants.py
torchseg/losses/dice.py
torchseg/losses/focal.py
torchseg/losses/jaccard.py
torchseg/losses/lovasz.py
torchseg/losses/mcc.py
torchseg/losses/soft_bce.py
torchseg/losses/soft_ce.py
torchseg/losses/tversky.py
torchseg-0.0.1a4.dist-info/LICENSE
torchseg-0.0.1a4.dist-info/METADATA
torchseg-0.0.1a4.dist-info/WHEEL
torchseg-0.0.1a4.dist-info/top_level.txt
torchseg-0.0.1a4.dist-info/RECORD
