Metadata-Version: 2.1
Name: torchseg
Version: 0.0.1a4
Summary: TorchSeg: Semantic Segmentation models for PyTorch
Author-email: Isaac Corley <isaac.corley@utsa.edu>
Maintainer-email: Isaac Corley <isaac.corley@utsa.edu>
License: MIT License
Project-URL: Homepage, https://github.com/isaaccorley/torchseg
Keywords: pytorch,deep learning,machine learning,computer vision,semantic segmentation
Classifier: Development Status :: 3 - Alpha
Classifier: Intended Audience :: Science/Research
Classifier: License :: OSI Approved :: MIT License
Classifier: Operating System :: OS Independent
Classifier: Programming Language :: Python :: 3
Classifier: Programming Language :: Python :: 3.9
Classifier: Programming Language :: Python :: 3.10
Classifier: Programming Language :: Python :: 3.11
Classifier: Topic :: Scientific/Engineering :: Artificial Intelligence
Requires-Python: >=3.9
License-File: LICENSE
Requires-Dist: einops >=0.7.0
Requires-Dist: timm >=0.9.12
Requires-Dist: torch >=1.13
Provides-Extra: all
Requires-Dist: torchseg[style,tests] ; extra == 'all'
Provides-Extra: style
Requires-Dist: black[jupyter] >=21.8 ; extra == 'style'
Requires-Dist: flake8 >=3.8 ; extra == 'style'
Requires-Dist: isort[colors] >=5.8 ; extra == 'style'
Requires-Dist: pyupgrade >=2.8 ; extra == 'style'
Provides-Extra: tests
Requires-Dist: pytest >=7.3 ; extra == 'tests'
Requires-Dist: pytest-cov >=4 ; extra == 'tests'
